pypgsync/__init__.py
pypgsync/mode/__init__.py
pypgsync/mode/appendonly.py
pypgsync/mode/primarykey.py
pypgsync/util/__init__.py
pypgsync/util/conversion.py
pypgsync/util/create.py
pypgsync/util/delete.py
pypgsync/util/log.py
pypgsync/util/query.py
pypgsync/util/update.py
pypgsync-1.2.0.dist-info/LICENSE
pypgsync-1.2.0.dist-info/WHEEL
pypgsync-1.2.0.dist-info/METADATA
pypgsync-1.2.0.dist-info/RECORD
