Metadata-Version: 2.1
Name: pypgsync
Version: 1.2.0
Summary: 
Home-page: https://github.com/danielschweigert/pypgsync
Author: Daniel Schweigert
Author-email: dan.schweigert@gmail.com
Requires-Python: >=3.8,<4.0
Classifier: Programming Language :: Python :: 3
Classifier: Programming Language :: Python :: 3.10
Classifier: Programming Language :: Python :: 3.8
Classifier: Programming Language :: Python :: 3.9
Requires-Dist: coverage-badge (>=1.1.0,<2.0.0)
Requires-Dist: psycopg[binary] (>=3.1.2,<4.0.0)
Requires-Dist: pytest-cov (>=3.0.0,<4.0.0)
Project-URL: Repository, https://github.com/danielschweigert/pypgsync
